torchdistill/__init__.py
torchdistill/common/__init__.py
torchdistill/common/constant.py
torchdistill/common/file_util.py
torchdistill/common/main_util.py
torchdistill/common/misc_util.py
torchdistill/common/module_util.py
torchdistill/common/tensor_util.py
torchdistill/common/yaml_util.py
torchdistill/core/__init__.py
torchdistill/core/distillation.py
torchdistill/core/forward_hook.py
torchdistill/core/training.py
torchdistill/core/util.py
torchdistill/core/interfaces/__init__.py
torchdistill/core/interfaces/forward_proc.py
torchdistill/core/interfaces/post_epoch_proc.py
torchdistill/core/interfaces/post_forward_proc.py
torchdistill/core/interfaces/pre_epoch_proc.py
torchdistill/core/interfaces/pre_forward_proc.py
torchdistill/core/interfaces/registry.py
torchdistill/datasets/__init__.py
torchdistill/datasets/registry.py
torchdistill/datasets/sample_loader.py
torchdistill/datasets/util.py
torchdistill/datasets/wrapper.py
torchdistill/losses/__init__.py
torchdistill/losses/high_level.py
torchdistill/losses/mid_level.py
torchdistill/losses/registry.py
torchdistill/losses/util.py
torchdistill/misc/__init__.py
torchdistill/misc/log.py
torchdistill/models/__init__.py
torchdistill/models/adaptation.py
torchdistill/models/official.py
torchdistill/models/registry.py
torchdistill/models/util.py
torchdistill/models/wrapper.py
torchdistill/models/classification/__init__.py
torchdistill/models/classification/densenet.py
torchdistill/models/classification/resnet.py
torchdistill/models/classification/wide_resnet.py
torchdistill/optim/__init__.py
torchdistill/optim/registry.py
torchdistill/optim/scheduler.py
torchdistill-1.1.3.dist-info/licenses/LICENSE
torchdistill-1.1.3.dist-info/METADATA
torchdistill-1.1.3.dist-info/WHEEL
torchdistill-1.1.3.dist-info/top_level.txt
torchdistill-1.1.3.dist-info/RECORD
