Metadata-Version: 2.4
Name: torchdistill
Version: 1.1.3
Summary: A Modular, Configuration-Driven Framework for Knowledge Distillation. Trained models, training logs and configurations are available for ensuring the reproducibility.
Home-page: https://github.com/yoshitomo-matsubara/torchdistill
Author: Yoshitomo Matsubara
License: MIT
Requires-Python: >=3.9
License-File: LICENSE
Requires-Dist: torch>=2.5.1
Requires-Dist: torchvision>=0.20.1
Requires-Dist: numpy
Requires-Dist: pyyaml>=6.0
Requires-Dist: scipy
Requires-Dist: cython
Provides-Extra: test
Requires-Dist: pytest; extra == "test"
Provides-Extra: docs
Requires-Dist: sphinx; extra == "docs"
Requires-Dist: sphinx_rtd_theme; extra == "docs"
Requires-Dist: sphinx_sitemap; extra == "docs"
Dynamic: author
Dynamic: description
Dynamic: description-content-type
Dynamic: home-page
Dynamic: license-file
Dynamic: provides-extra
Dynamic: requires-dist
Dynamic: requires-python
Dynamic: summary
